{
	"type": "minecraft:entity",
	"pools": [
		{
			"rolls": 1,
			"entries": [
				{
					"type": "minecraft:item",
					"name": "minecraft:command_block",
					"functions": [
						{
							"function": "minecraft:set_count",
							"count": {
								"min": 24,
								"max": 42
							},
							"add": false
						},
						{
							"function": "minecraft:copy_nbt",
							"source": {
								"type": "minecraft:storage",
								"source": "stardust:items"
							},
							"ops": [
								{
									"source": "all.2013005.tag",
									"target": "{}",
									"op": "merge"
								}
							]
						}
					]
				}
			]
		},
		{
			"rolls": 1,
			"bonus_rolls": 0,
			"entries": [
				{
					"type": "minecraft:item",
					"name": "minecraft:command_block",
					"functions": [
						{
							"function": "minecraft:set_count",
							"count": {
								"min": 24,
								"max": 42
							},
							"add": false
						},
						{
							"function": "minecraft:copy_nbt",
							"source": {
								"type": "minecraft:storage",
								"source": "stardust:items"
							},
							"ops": [
								{
									"source": "all.2013002.tag",
									"target": "{}",
									"op": "merge"
								}
							]
						}
					]
				}
			]
		}
	]
}
